arrow_mssql/__init__.py
arrow_mssql/connector.py
arrow_mssql/export.py
arrow_mssql/input/__init__.py
arrow_mssql/input/datatypes.py
arrow_mssql/input/schema.py
arrow_mssql/iport.py
arrow_mssql/output/__init__.py
arrow_mssql/output/datatypes.py
arrow_mssql/output/schemas.py
arrow_mssql/utils.py
arrow_mssql-0.0.89.dist-info/METADATA
arrow_mssql-0.0.89.dist-info/WHEEL
arrow_mssql-0.0.89.dist-info/RECORD
