Metadata-Version: 2.3
Name: arrow-mssql
Version: 0.0.89
Summary: Arrow-mssql exporta tabela ou consulta para .parquet ou .csv, e também faz a leitura de .parquet ou .csv para tabela do sql server
Author: Marcus Holanda
Author-email: mvsh777@hotmail.com
Requires-Python: >=3.11,<4.0
Classifier: Development Status :: 1 - Planning
Classifier: Natural Language :: Portuguese (Brazilian)
Classifier: Programming Language :: PL/SQL
Classifier: Programming Language :: Python :: 3
Classifier: Programming Language :: Python :: 3.11
Classifier: Programming Language :: Python :: 3.12
Classifier: Programming Language :: Python :: 3.13
Requires-Dist: pyarrow (>=15,<23)
Requires-Dist: pyodbc (>=5.1.0,<6.0.0)
Requires-Dist: sqlglot (>=20,<28)
Project-URL: Codigo, https://github.com/Marcus-Holanda777/arrow-mssql
